cldfbench/__init__.py
cldfbench/__main__.py
cldfbench/catalogs.py
cldfbench/ci.py
cldfbench/cldf.py
cldfbench/cli_util.py
cldfbench/datadir.py
cldfbench/dataset.py
cldfbench/metadata.py
cldfbench/scaffold.py
cldfbench/util.py
cldfbench/commands/README.md
cldfbench/commands/__init__.py
cldfbench/commands/catconfig.py
cldfbench/commands/catinfo.py
cldfbench/commands/catupdate.py
cldfbench/commands/check.py
cldfbench/commands/ci.py
cldfbench/commands/cldfreadme.py
cldfbench/commands/diff.py
cldfbench/commands/download.py
cldfbench/commands/geojson.py
cldfbench/commands/info.py
cldfbench/commands/ls.py
cldfbench/commands/makecldf.py
cldfbench/commands/media.py
cldfbench/commands/new.py
cldfbench/commands/readme.py
cldfbench/commands/run.py
cldfbench/commands/stub.py
cldfbench/commands/zenodo.py
cldfbench/dataset_template/+prefix+_+id+.py_tmpl
cldfbench/dataset_template/.gitignore
cldfbench/dataset_template/pyproject.toml
cldfbench/dataset_template/setup.cfg
cldfbench/dataset_template/setup.py_tmpl
cldfbench/dataset_template/test.py
cldfbench/dataset_template/.github/workflows/cldf-validation.yml
cldfbench/dataset_template/cldf/.gitattributes
cldfbench/dataset_template/cldf/README.md
cldfbench/dataset_template/etc/README.md
cldfbench/dataset_template/raw/README.md
cldfbench-1.14.2.dist-info/LICENSE
cldfbench-1.14.2.dist-info/METADATA
cldfbench-1.14.2.dist-info/WHEEL
cldfbench-1.14.2.dist-info/entry_points.txt
cldfbench-1.14.2.dist-info/top_level.txt
cldfbench-1.14.2.dist-info/RECORD
