Metadata-Version: 2.1
Name: cldfbench
Version: 1.14.2
Summary: Python library implementing a CLDF workbench
Home-page: https://github.com/cldf/cldfbench
Author: Robert Forkel
Author-email: dlce.rdm@eva.mpg.de
License: Apache 2.0
Project-URL: Bug Tracker, https://github.com/cldf/cldfbench/issues
Classifier: Development Status :: 5 - Production/Stable
Classifier: Intended Audience :: Developers
Classifier: Intended Audience :: Science/Research
Classifier: Natural Language :: English
Classifier: Operating System :: OS Independent
Classifier: Programming Language :: Python :: 3
Classifier: Programming Language :: Python :: 3.8
Classifier: Programming Language :: Python :: 3.9
Classifier: Programming Language :: Python :: 3.10
Classifier: Programming Language :: Python :: 3.11
Classifier: Programming Language :: Python :: 3.12
Classifier: Programming Language :: Python :: 3.13
Classifier: Programming Language :: Python :: Implementation :: CPython
Classifier: Programming Language :: Python :: Implementation :: PyPy
Classifier: License :: OSI Approved :: Apache Software License
Requires-Python: >=3.8
License-File: LICENSE
Requires-Dist: rfc3986<2
Requires-Dist: csvw>=1.5.6
Requires-Dist: clldutils>=3.10.0
Requires-Dist: cldfcatalog>=1.5.1
Requires-Dist: pycldf>=1.19.0
Requires-Dist: termcolor
Requires-Dist: requests
Requires-Dist: appdirs
Requires-Dist: pytest
Requires-Dist: zenodoclient>=0.3
Requires-Dist: simplepybtex
Requires-Dist: tqdm
Provides-Extra: clts
Requires-Dist: pyclts; extra == "clts"
Provides-Extra: concepticon
Requires-Dist: pyconcepticon; extra == "concepticon"
Provides-Extra: dev
Requires-Dist: flake8; extra == "dev"
Requires-Dist: wheel; extra == "dev"
Requires-Dist: build; extra == "dev"
Requires-Dist: twine; extra == "dev"
Provides-Extra: docs
Requires-Dist: sphinx<7; extra == "docs"
Requires-Dist: sphinx-autodoc-typehints; extra == "docs"
Requires-Dist: sphinx-rtd-theme; extra == "docs"
Provides-Extra: excel
Requires-Dist: openpyxl; extra == "excel"
Requires-Dist: xlrd>=2; extra == "excel"
Provides-Extra: glottolog
Requires-Dist: pyglottolog; extra == "glottolog"
Provides-Extra: odf
Requires-Dist: odfpy; extra == "odf"
Provides-Extra: test
Requires-Dist: packaging; extra == "test"
Requires-Dist: pytest>=5; extra == "test"
Requires-Dist: pytest-mock; extra == "test"
Requires-Dist: pytest-cov; extra == "test"
Requires-Dist: tox; extra == "test"
Requires-Dist: pyglottolog>=3.2.2; extra == "test"
Requires-Dist: pyconcepticon; extra == "test"
Requires-Dist: odfpy; extra == "test"
Requires-Dist: openpyxl; extra == "test"
Requires-Dist: xlrd>=2; extra == "test"
